django_util/__init__.py
django_util/apps.py
django_util/autocompletes.py
django_util/models.py
Django_Util-0.0.5.dist-info/LICENSE
Django_Util-0.0.5.dist-info/METADATA
Django_Util-0.0.5.dist-info/WHEEL
Django_Util-0.0.5.dist-info/top_level.txt
Django_Util-0.0.5.dist-info/RECORD
