Metadata-Version: 2.1
Name: Django-Util
Version: 0.0.5
Summary: Django Utililies
Home-page: https://github.com/TheVinhLuong102/Django-Util
Author: TheVinhLuong102
Author-email: TheVinhLuong@GMail.com
License: UNKNOWN
Keywords: Django Utililies
Platform: UNKNOWN
Requires-Dist: Django (>=3.1.7)
